deepspeed/__init__.py
deepspeed/constants.py
deepspeed/env_report.py
deepspeed/git_version_info.py
deepspeed/git_version_info_installed.py
deepspeed/accelerator/__init__.py
deepspeed/accelerator/abstract_accelerator.py
deepspeed/accelerator/cpu_accelerator.py
deepspeed/accelerator/cuda_accelerator.py
deepspeed/accelerator/hpu_accelerator.py
deepspeed/accelerator/mlu_accelerator.py
deepspeed/accelerator/mps_accelerator.py
deepspeed/accelerator/npu_accelerator.py
deepspeed/accelerator/real_accelerator.py
deepspeed/accelerator/sdaa_accelerator.py
deepspeed/accelerator/xpu_accelerator.py
deepspeed/autotuning/__init__.py
deepspeed/autotuning/autotuner.py
deepspeed/autotuning/config.py
deepspeed/autotuning/constants.py
deepspeed/autotuning/scheduler.py
deepspeed/autotuning/utils.py
deepspeed/autotuning/tuner/__init__.py
deepspeed/autotuning/tuner/base_tuner.py
deepspeed/autotuning/tuner/cost_model.py
deepspeed/autotuning/tuner/index_based_tuner.py
deepspeed/autotuning/tuner/model_based_tuner.py
deepspeed/autotuning/tuner/utils.py
deepspeed/checkpoint/__init__.py
deepspeed/checkpoint/constants.py
deepspeed/checkpoint/deepspeed_checkpoint.py
deepspeed/checkpoint/ds_to_universal.py
deepspeed/checkpoint/reshape_3d_utils.py
deepspeed/checkpoint/reshape_meg_2d.py
deepspeed/checkpoint/reshape_utils.py
deepspeed/checkpoint/universal_checkpoint.py
deepspeed/checkpoint/utils.py
deepspeed/checkpoint/zero_checkpoint.py
deepspeed/comm/__init__.py
deepspeed/comm/backend.py
deepspeed/comm/ccl.py
deepspeed/comm/comm.py
deepspeed/comm/config.py
deepspeed/comm/constants.py
deepspeed/comm/reduce_op.py
deepspeed/comm/torch.py
deepspeed/comm/utils.py
deepspeed/compression/__init__.py
deepspeed/compression/basic_layer.py
deepspeed/compression/compress.py
deepspeed/compression/config.py
deepspeed/compression/constants.py
deepspeed/compression/helper.py
deepspeed/compression/scheduler.py
deepspeed/compression/utils.py
deepspeed/elasticity/__init__.py
deepspeed/elasticity/config.py
deepspeed-0.16.5.dist-info/LICENSE
deepspeed-0.16.5.dist-info/METADATA
deepspeed-0.16.5.dist-info/WHEEL
deepspeed-0.16.5.dist-info/entry_points.txt
deepspeed-0.16.5.dist-info/top_level.txt
deepspeed-0.16.5.dist-info/RECORD
