Metadata-Version: 2.1
Name: deepspeed
Version: 0.16.5
Summary: DeepSpeed library
Home-page: http://deepspeed.ai
Author: DeepSpeed Team
Author-email: deepspeed-info@microsoft.com
License: Apache Software License 2.0
Project-URL: Documentation, https://deepspeed.readthedocs.io
Project-URL: Source, https://github.com/deepspeedai/DeepSpeed
Classifier: Programming Language :: Python :: 3.8
Classifier: Programming Language :: Python :: 3.9
Classifier: Programming Language :: Python :: 3.10
Classifier: Programming Language :: Python :: 3.11
Classifier: Programming Language :: Python :: 3.12
License-File: LICENSE
Requires-Dist: einops
Requires-Dist: hjson
Requires-Dist: msgpack
Requires-Dist: ninja
Requires-Dist: numpy
Requires-Dist: packaging >=20.0
Requires-Dist: psutil
Requires-Dist: py-cpuinfo
Requires-Dist: pydantic >=2.0.0
Requires-Dist: torch
Requires-Dist: tqdm
Requires-Dist: nvidia-ml-py
Provides-Extra: 1bit
Requires-Dist: cupy-cuda12x ; extra == '1bit'
Provides-Extra: 1bit_mpi
Requires-Dist: mpi4py ; extra == '1bit_mpi'
Requires-Dist: cupy-cuda12x ; extra == '1bit_mpi'
Provides-Extra: all
Requires-Dist: pytest-xdist ; extra == 'all'
Requires-Dist: torch ; extra == 'all'
Requires-Dist: diffusers >=0.25.0 ; extra == 'all'
Requires-Dist: transformers >=4.32.1 ; extra == 'all'
Requires-Dist: google ; extra == 'all'
Requires-Dist: pytest >=7.2.0 ; extra == 'all'
Requires-Dist: triton ==1.0.0 ; extra == 'all'
Requires-Dist: neural-compressor ==2.1.0 ; extra == 'all'
Requires-Dist: future ; extra == 'all'
Requires-Dist: py-cpuinfo ; extra == 'all'
Requires-Dist: wandb ; extra == 'all'
Requires-Dist: transformers >=4.39.0 ; extra == 'all'
Requires-Dist: torchvision ; extra == 'all'
Requires-Dist: qtorch ; extra == 'all'
Requires-Dist: hjson ; extra == 'all'
Requires-Dist: sphinx ; extra == 'all'
Requires-Dist: docutils <0.18 ; extra == 'all'
Requires-Dist: triton ==2.1.0 ; extra == 'all'
Requires-Dist: accelerate ; extra == 'all'
Requires-Dist: tensorboard ; extra == 'all'
Requires-Dist: recommonmark ; extra == 'all'
Requires-Dist: packaging ; extra == 'all'
Requires-Dist: sphinx-rtd-theme ; extra == 'all'
Requires-Dist: clang-format ==18.1.3 ; extra == 'all'
Requires-Dist: lm-eval ==0.3.0 ; extra == 'all'
Requires-Dist: importlib-metadata >=4 ; extra == 'all'
Requires-Dist: protobuf ; extra == 'all'
Requires-Dist: tabulate ; extra == 'all'
Requires-Dist: qtorch ==0.3.0 ; extra == 'all'
Requires-Dist: xgboost ; extra == 'all'
Requires-Dist: mpi4py ; extra == 'all'
Requires-Dist: comet-ml >=3.41.0 ; extra == 'all'
Requires-Dist: pydantic >=2.0.0 ; extra == 'all'
Requires-Dist: autodoc-pydantic >=2.0.0 ; extra == 'all'
Requires-Dist: tqdm ; extra == 'all'
Requires-Dist: cupy-cuda12x ; extra == 'all'
Requires-Dist: pytest-randomly ; extra == 'all'
Requires-Dist: mup ; extra == 'all'
Requires-Dist: safetensors ; extra == 'all'
Requires-Dist: sentencepiece ; extra == 'all'
Requires-Dist: triton >=2.1.0 ; extra == 'all'
Requires-Dist: psutil ; extra == 'all'
Requires-Dist: pre-commit >=3.2.0 ; extra == 'all'
Requires-Dist: pytest-forked ; extra == 'all'
Requires-Dist: deepspeed-kernels ; (sys_platform == "linux") and extra == 'all'
Provides-Extra: autotuning
Requires-Dist: tabulate ; extra == 'autotuning'
Provides-Extra: autotuning_ml
Requires-Dist: hjson ; extra == 'autotuning_ml'
Requires-Dist: tabulate ; extra == 'autotuning_ml'
Requires-Dist: xgboost ; extra == 'autotuning_ml'
Provides-Extra: dev
Requires-Dist: accelerate ; extra == 'dev'
Requires-Dist: clang-format ==18.1.3 ; extra == 'dev'
Requires-Dist: comet-ml >=3.41.0 ; extra == 'dev'
Requires-Dist: docutils <0.18 ; extra == 'dev'
Requires-Dist: future ; extra == 'dev'
Requires-Dist: importlib-metadata >=4 ; extra == 'dev'
Requires-Dist: mup ; extra == 'dev'
Requires-Dist: pre-commit >=3.2.0 ; extra == 'dev'
Requires-Dist: pytest >=7.2.0 ; extra == 'dev'
Requires-Dist: pytest-forked ; extra == 'dev'
Requires-Dist: pytest-randomly ; extra == 'dev'
Requires-Dist: pytest-xdist ; extra == 'dev'
Requires-Dist: qtorch ==0.3.0 ; extra == 'dev'
Requires-Dist: recommonmark ; extra == 'dev'
Requires-Dist: sphinx ; extra == 'dev'
Requires-Dist: sphinx-rtd-theme ; extra == 'dev'
Requires-Dist: tensorboard ; extra == 'dev'
Requires-Dist: torchvision ; extra == 'dev'
Requires-Dist: transformers >=4.39.0 ; extra == 'dev'
Requires-Dist: wandb ; extra == 'dev'
Requires-Dist: deepspeed-kernels ; (sys_platform == "linux") and extra == 'dev'
Provides-Extra: inf
Requires-Dist: google ; extra == 'inf'
Requires-Dist: lm-eval ==0.3.0 ; extra == 'inf'
Requires-Dist: protobuf ; extra == 'inf'
Requires-Dist: qtorch ; extra == 'inf'
Requires-Dist: safetensors ; extra == 'inf'
Requires-Dist: sentencepiece ; extra == 'inf'
Requires-Dist: transformers >=4.32.1 ; extra == 'inf'
Provides-Extra: readthedocs
Requires-Dist: autodoc-pydantic >=2.0.0 ; extra == 'readthedocs'
Requires-Dist: docutils <0.18 ; extra == 'readthedocs'
Requires-Dist: hjson ; extra == 'readthedocs'
Requires-Dist: packaging ; extra == 'readthedocs'
Requires-Dist: psutil ; extra == 'readthedocs'
Requires-Dist: py-cpuinfo ; extra == 'readthedocs'
Requires-Dist: pydantic >=2.0.0 ; extra == 'readthedocs'
Requires-Dist: recommonmark ; extra == 'readthedocs'
Requires-Dist: sphinx-rtd-theme ; extra == 'readthedocs'
Requires-Dist: torch ; extra == 'readthedocs'
Requires-Dist: tqdm ; extra == 'readthedocs'
Provides-Extra: sd
Requires-Dist: diffusers >=0.25.0 ; extra == 'sd'
Requires-Dist: triton >=2.1.0 ; extra == 'sd'
Provides-Extra: sparse
Requires-Dist: neural-compressor ==2.1.0 ; extra == 'sparse'
Provides-Extra: sparse_attn
Requires-Dist: triton ==1.0.0 ; extra == 'sparse_attn'
Provides-Extra: triton
Requires-Dist: triton ==2.1.0 ; extra == 'triton'
